odoo/addons/mail_optional_autofollow/README.rst
odoo/addons/mail_optional_autofollow/__init__.py
odoo/addons/mail_optional_autofollow/__manifest__.py
odoo/addons/mail_optional_autofollow/i18n/ca.po
odoo/addons/mail_optional_autofollow/i18n/de.po
odoo/addons/mail_optional_autofollow/i18n/es.po
odoo/addons/mail_optional_autofollow/i18n/es_CO.po
odoo/addons/mail_optional_autofollow/i18n/fr.po
odoo/addons/mail_optional_autofollow/i18n/hr.po
odoo/addons/mail_optional_autofollow/i18n/it.po
odoo/addons/mail_optional_autofollow/i18n/mail_optional_autofollow.pot
odoo/addons/mail_optional_autofollow/i18n/pt_BR.po
odoo/addons/mail_optional_autofollow/i18n/sl.po
odoo/addons/mail_optional_autofollow/readme/CONTRIBUTORS.md
odoo/addons/mail_optional_autofollow/readme/CREDITS.md
odoo/addons/mail_optional_autofollow/readme/DESCRIPTION.md
odoo/addons/mail_optional_autofollow/readme/USAGE.md
odoo/addons/mail_optional_autofollow/static/description/autofollow.png
odoo/addons/mail_optional_autofollow/static/description/icon.png
odoo/addons/mail_optional_autofollow/static/description/index.html
odoo/addons/mail_optional_autofollow/tests/__init__.py
odoo/addons/mail_optional_autofollow/tests/test_mail_optional_autofollow.py
odoo/addons/mail_optional_autofollow/wizard/__init__.py
odoo/addons/mail_optional_autofollow/wizard/mail_compose_message.py
odoo/addons/mail_optional_autofollow/wizard/mail_compose_message_view.xml
odoo_addon_mail_optional_autofollow-19.0.1.0.0.2.dist-info/METADATA
odoo_addon_mail_optional_autofollow-19.0.1.0.0.2.dist-info/WHEEL
odoo_addon_mail_optional_autofollow-19.0.1.0.0.2.dist-info/top_level.txt
odoo_addon_mail_optional_autofollow-19.0.1.0.0.2.dist-info/RECORD
