Metadata-Version: 2.1
Name: odoo-addon-mail_optional_autofollow
Version: 19.0.1.0.0.2
Requires-Dist: odoo==19.0.*
Summary: Choose if you want to automatically add new recipients as followers on mail.compose.message
Home-page: https://github.com/OCA/mail
License: AGPL-3
Author: ACSONE SA/NV,Odoo Community Association (OCA)
Author-email: support@odoo-community.org
Classifier: Programming Language :: Python
Classifier: Framework :: Odoo
Classifier: Framework :: Odoo :: 19.0
Classifier: License :: OSI Approved :: GNU Affero General Public License v3
